dummyML/__init__.py
dummyML/automate_analysis.py
dummyML/automate_modeling_evaluation.py
dummyML/preprocessing.py
dummyML/utilities.py
dummyML/version.py
dummyML/evaluate_models/__init__.py
dummyML/evaluate_models/classification_metrics.py
dummyML/evaluate_models/classification_metrics_imb_cutoff.py
dummyML/evaluate_models/regression_metrics.py
dummyML/select_fit_models/__init__.py
dummyML/select_fit_models/classification_models.py
dummyML/select_fit_models/imbalanced_classification_models.py
dummyML/select_fit_models/regression_models.py
dummyML-0.9.7.dist-info/LICENSE.txt
dummyML-0.9.7.dist-info/METADATA
dummyML-0.9.7.dist-info/WHEEL
dummyML-0.9.7.dist-info/top_level.txt
dummyML-0.9.7.dist-info/RECORD
